{"QWg9UrYKS3P+ra6mjFstxg==":"dsc01188-2000x1124.jpeg","P6fqyNUtLnOoGx2HA4OT+Q==":"dsc01188-1-2000x1124.jpeg","eJjwKyS7qt0rLrDAPTVPNQ==":"dsc01157-2000x1124.jpeg","qWZRBa57z72pKk4mwQL1Xw==":"dsc01157-1-2000x1124.jpeg","wZAzF/0jwXcxqzKMhugawg==":"lady%20na%20moeda-44-2000x1500.jpeg","/RU0uLhK2u8GcAgkFWlkvg==":"lady%20na%20moeda-43-2000x1500.jpeg","4z+bD6g86EVHRc7gK7zJYQ==":"lady%20na%20moeda-30-2000x1500.jpeg","t/mo4lvmx6eOKyJMEngZfA==":"lady%20na%20moeda-34-2000x1500.jpeg","HubRaUcXq8FMLvyiEPbg2w==":"lady%20na%20moeda-44-2000x1500.jpeg","C9WgBXV4gguWtD4+YpVIFg==":"img-3872-2000x2667.jpeg","sOoyPHRvhmh0KdicMGLhww==":"img-3881-2000x1500.jpg","sYIDRId+ce0Ltl1FmB3Ucw==":"121667af-63e7-4443-8a11-2a6a4c6ab689-1200x1599.jpeg","2HiGPrekfD9Uri9ynfz79w==":"lady%20na%20moeda-43-2000x1500.jpeg","xnEqZhpvBmjP8u1BZp/kGg==":"121667af-63e7-4443-8a11-2a6a4c6ab689-1-1200x1599.jpeg","ItAkyF5hdVHQ2SPaqgOZ6A==":"121667af-63e7-4443-8a11-2a6a4c6ab689-2-1200x1599.jpeg","5xbfKhVxs1QNLeLT6Qw/dw==":"121667af-63e7-4443-8a11-2a6a4c6ab689-3-1200x1599.jpeg","kZzdBa6HT9ky/dixw90Ctg==":"lady%20na%20moeda-43-2000x1500.jpeg","1w+DeZDKKmosngfBwnwUgw==":"estampa1-122x168.png","DTnBrxoegPVEG/g8oe0DNg==":"estampa1invertida-01-01-1-96x136.png","nSz9mmFXstzuGn5B//1XAw==":"estampa1invertida-01-01-2-96x136.png","Vfr9oGqITmnhRPxKjRHoaw==":"estampa1-1-122x168.png","1FzrCmTFTerJevBK8FetMQ==":"lrm_export_180353617608364_20181119-105741140-2000x1500.jpg","q2yjhAzgN95O2xsHKFw0OQ==":"background%20agenda-960x960.jpg","6bKxNqUifDyB0Gc4En47qg==":"background%20agenda-960x960.jpeg","vvgmBAu4ubhfhhxfne76Kg==":"background%20agenda-960x960.jpeg","Yk9/rz72kSLmFhpEfdL7CQ==":"whatsapp%20image%202020-01-28%20at%204.32.28%20pm-676x676.jpg","1htTEYDfyVxAXEf8wcWzrA==":"whatsapp%20image%202020-01-28%20at%204.34.48%20pm-676x676.jpg","vZfH5/+2DVzc1PjKtbMU0Q==":"whatsapp%20image%202020-01-28%20at%204.36.30%20pm-676x676.jpg","urdxLRLx9JjAL1aKdrk8bA==":"estampa1invertida-01-01-1-106x150.png","DDpdzskqHtkSekppi1IV2w==":"boa11-2000x1124.jpg","TlcgjS4qEN3prj4uZ9fr5Q==":"estampa1invertida-01-01-2-106x150.png","l7ZNQmTLIhyvi+xxm3Ms2A==":"estampa1invertida-01-01-3-106x150.png","OM6hTwqMAQpTVhLcPG86xg==":"background1.jpg","pa5Dkwo/T1qgW/t0h+fQvA==":"background5.jpg","sT80Y4RCGNBrSInGgrjIuA==":"background3.jpg","UAc7kepzJPkrSn4uqTRvmw==":"background4.jpg","mIIbxW0r7dEZSbMPwcoYdg==":"background2.jpg","NpPIVFTQ56/LIHC/waGiNg==":"whatsapp%20image%202020-01-28%20at%204.36.30%20pm-1080x1080.jpg","xC8r1QLLp2j/l4Yf5EUqdA==":"whatsapp%20image%202020-01-28%20at%204.34.48%20pm-1080x1080.jpg","re5flBfOW1vFndZhIUgxPQ==":"lady%20na%20moeda-44-736x552.jpg","Gk7FZr/zcYIzMVpojuds8g==":"estampa1invertida-01-01-1-122x173.png","S1gkCPjskaF55GTATnEjkA==":"estampa1invertida-01-01-1-102x144.png","sf6tYablwc4zAZd8lQVxTw==":"estampa1invertida-01-01-2-102x144.png","BW764YsJzOiN6huKBU1KkA==":"c1a6c1c9-010e-45e9-9e89-c7105c468066-1200x1599.jpg","/jl0Zp7JJWdVI4BhMsx0kQ==":"c1a6c1c9-010e-45e9-9e89-c7105c468066-1200x1599.jpeg","5f9k66czjuoVun9WCtd+GQ==":"c1a6c1c9-010e-45e9-9e89-c7105c468066-1-1200x1599.jpeg","1af0G8epjmhnUEf4VQpetg==":"ladylist-1046x1046.jpg","VD6jktmnahM6BJGGSDYCfg==":"quiz-1046x1046.jpg","zJi0FEzw5b+zEQiNZGlmUA==":"background1.jpeg","X+NFHMzVHv4Sq+l1bMc/yQ==":"dsc01157-596x335.jpeg","9y9nXAd3jM6p7OT1AzC9Ag==":"dsc01183-596x335.jpeg","ImZKAeETMxf4/1P/ulpoPA==":"dsc01147-596x335.jpeg","kiFbbGadBnAojgq/B4Jmng==":"dsc01222-596x335.jpeg","VXBTseUp451hL4x3x+ebUg==":"dsc01190-736x414.jpg","f2BfTiufuJSIqxPBveYRkQ==":"c1a6c1c9-010e-45e9-9e89-c7105c468066-732x975.jpg","v7cv0u3Hg/ctQIXbbyK7rg==":"c1a6c1c9-010e-45e9-9e89-c7105c468066-732x975.jpeg","aDYiZWw528eVf+7cD6VMHA==":"releasefoto-952x952.jpg","tyQ5QT8psEukPgBXpa8IHQ==":"ladyrelease-952x584.jpg","C6pXcxMuHRH6L4GNXxzk2A==":"20200131_132319-2-1746x1240.png","HLFu0knCSNGxS4YBSHcBTw==":"20200131_132319-3-1746x1240.png","JGpBHTT+YtDLiMgYpezkIQ==":"20200131_132319-4-1746x1240.png","zL8mUPNHM7cAeFTnomcuDA==":"20200131_132319-5-1746x1240.png","E4FzuM7gcbGqmvalPTfp0g==":"20200131_132319-6-1746x1240.png","Z//R5mM5pKtCudvMR/+2zw==":"estampa1invertida-01-01-1-936x1324.png","60i0JA1/izmLrQ8JzdWtKA==":"estampa1invertida-01-01-2-936x1324.png","0JJNX5o7sEQfkn5evRKZCg==":"estampa1invertida-01-01-3-936x1324.png","rN12Kb8xP5VdprZ7G12ypg==":"estampa1-936x1289.png","o2d1AmfWybd9AhL5EV/muw==":"whatsapp%20image%202020-01-13%20at%208.39.37%20am%20(1)-1280x640.jpeg","pVq90WGIamszYHThCdd9Ug==":"whatsapp%20image%202020-01-13%20at%208.39.37%20am%20(1)-1280x640.jpeg","nnpJKT190c2eDIp1a4pOTQ==":"whatsapp%20image%202020-01-13%20at%208.39.37%20am%20(1)-1280x640.jpeg","/Gk7S10hSSyMJbJlVB3E2w==":"whatsapp%20image%202018-11-12%20at%2012.13.41%20pm-640x640.jpeg","1Alifp9sSNQcURFC6kfBNw==":"lady%20camisa-1280x640.jpg","jFv+MyrxM/s6jsMp5KWIbg==":"lady%20camisa-1280x640.jpeg","vIYAkrj4enwg4xBtXhi5fg==":"lady%20camisa-1280x640.jpeg","0zAeEoz6/3O/Ho7XSXXkHw==":"estampa1-1-936x1289.png","OjPNlgfdUJHTTvOLtwyTBg==":"whatsapp%20image%202020-03-07%20at%2011.04.18-436x261.jpg","wMniJ/BMa/SPdbcRUqogiw==":"whatsapp%20image%202020-03-07%20at%2011.26.55-744x704.jpeg","6KaBN4uKqR8JTvftWimWkw==":"whatsapp%20image%202020-03-07%20at%2011.26.55%20(1)-744x455.jpg","23XdFvGn8G3ueOAGuwH/mQ==":"ladyrelease-1280x785.jpeg","ZCoipAyKnLTuGzBnsrSpdg==":"ladyrelease-1-1280x785.jpeg","NHZfFY1T5xO0IKyfmLgFyQ==":"img-9207-420x259.jpeg","0QQ2LeAtZe7gIdwd+dRfAQ==":"dsc01186-420x236.jpeg","lWUFFThXWtov7Fuxf/XkvA==":"dsc00714-420x236.jpeg","uJDoO3stB696pSsVmoYDlw==":"boa19-420x747.jpeg","tpePkkWViVupa8xz1Ozjhg==":"ladyrelease-2-1280x785.jpeg","F5otZSY+0zrRIcr919wLMw==":"whatsapp%20image%202020-03-07%20at%2012.25.43-744x744.jpeg","MLnBe4kfwlbbEIgsbHXm6w==":"whatsapp%20image%202020-03-07%20at%2012.39.47-1080x1052.jpg","uUF1YVTzq4KFS3Jt9qZhqQ==":"5-676x676.jpg","WgBpAlE1ZTdZbIgcOP9O3w==":"whatsapp%20image%202020-03-09%20at%2011.39.20-540x1103.jpg","DmyBRY9xxjeIgLhtZHX43A==":"whatsapp%20image%202020-01-13%20at%208.39.37%20am%20(1)-1280x640.jpg","mUmMUvh6xYJAHnLdao+8AA==":"hq%20lady-1366x768.png","cRZAwaNZ7f3nZtpbVWGCLA==":"whatsapp%20image%202020-03-09%20at%2014.57.18-1080x960.jpg","rpOBx5nrDeFG2wHLqg3ccQ==":"whatsapp%20image%202020-03-09%20at%2015.00.18-777x1280.jpeg","/txTbmwxwdSib7DwE4Ks2g==":"whatsapp%20image%202020-03-09%20at%2015.00.18-710x1170.jpg","NnoCfFHte9gE7AnnFUUOHA==":"ladyrelease-3-1280x785.jpeg","etk0D2zRWyLoqzvTRozMXQ==":"whatsapp%20image%202019-08-21%20at%2011.11.16%20am-960x960.jpg","fTx4wcVayy4238D2k9nklw==":"whatsapp%20image%202020-03-12%20at%2011.13.50-744x442.jpg","4ijryWukDUA3KyfkYRlOPg==":"whatsapp%20image%202020-03-12%20at%2012.32.37-744x992.jpeg","RIdjy9sCq717zsGrjXE7jQ==":"whatsapp%20image%202020-03-12%20at%2013.53.58-1080x1071.jpg","KzMobt7BaUPiqx3LPZ4Ecg==":"whatsapp%20image%202020-03-12%20at%2019.47.57-744x1163.jpg","6akKmrZhyPgktH5jaqcfsg==":"whatsapp%20image%202020-04-06%20at%2009.35.49-744x419.jpeg","HJJdsRBXr94I8JQuiV+1vA==":"whatsapp%20image%202020-04-06%20at%2010.31.12-720x1280.jpg","gCMOx+CdAZno/nz2LlWZTA==":"whatsapp%20image%202020-04-06%20at%2012.01.16-720x1280.jpg","YURLW6Np1TZ/7KC9+Q1dXw==":"whatsapp%20image%202020-04-06%20at%2011.59.58-680x1209.jpg","gUTrM0bR6r2b1QOCXs+BEQ==":"whatsapp%20image%202020-04-06%20at%2011.59.58-680x1209.jpeg","+izAm53XakbNiDyJ8NjGYA==":"whatsapp%20image%202020-04-06%20at%2012.05.21-680x1209.jpg","7CBpB+rHbYcW00Nfc0uCFA==":"whatsapp%20image%202020-04-06%20at%2012.14.29%20(1)-720x1280.jpg","pdWgk4s/CsJBHhKUXadP8A==":"whatsapp%20image%202020-04-06%20at%2013.06.50-720x1280.jpg","5fLMWjteXv2cGmieOfRX2g==":"whatsapp%20image%202020-04-06%20at%2010.31.12-720x1280.jpeg","POO7YxslIir//MqdYWuP7A==":"whatsapp%20image%202020-04-06%20at%2014.22.26-708x1248.jpg","v0vUu3nV52NxGBkvJB69Yg==":"whatsapp%20image%202020-04-06%20at%2013.35.56-1080x1080.jpg","RI2WzfJbsNyehP7DU9cVkA==":"baha-664x1180.jpg","fCrcx8X/9rTPv0jnmW5I8w==":"baharemoso-664x1171.jpg","5BPSX3a6nU0v+e8qTNoT/w==":"baharemoso-680x1199.jpg","Bfa+qXjQfURwAUuIZZrE+g==":"baharemoso-680x1199.jpeg","7PotLOCdNHYWh/LWE/wcWA==":"bahosidade-680x1209.jpg","LYO4E/LqB1uQBOWHciZaNQ==":"123-632x1124.jpg","QRwK++RqY+dA+IrIv/IVIw==":"123-632x1124.jpeg","bz8kC9aGNMGBXtAMWKuzYg==":"123-1-632x1124.jpeg","xF03zTG6M7xtbS3FsfXHGQ==":"whatsapp%20image%202020-04-06%20at%2016.12.04-632x1124.jpg","XHNeSFAGWeB9AhAsixblrA==":"baha3-680x1209.jpg","hyPmLgm7j/nOX+TMXaRjcw==":"baha-612x876.png","yA3bhjPHrzxaciQNt/cfHA==":"baha3-1-680x1209.jpg","ZHCHEmGknIB9avo38c/5mQ==":"baha-1-612x876.png","V+TKu846o+H8wv/nB0+IMw==":"recife%20free%20to%20use-300x168.jpg","Yd27f9texZrDiVFgM7NSrQ==":"pexels-photo-1863939-1880x1253.jpg","4ZNg1EgXopxzdBTg9pzcNg==":"pexels-photo-1863939-1880x1253.jpeg","vER1Hm0wwGz3hg8vJouvBQ==":"whatsapp%20image%202020-04-08%20at%2012.06.00-306x307.jpg","0uPmwH8ztbnhGZNgDPTODw==":"whatsapp%20image%202020-04-08%20at%2012.07.29-306x310.jpg","/ToJr0zGAVCE/sF2SatJ7g==":"whatsapp%20image%202020-04-08%20at%2012.07.29-306x310.jpeg","P/aZETVAxnSWIAQdg1cR2A==":"whatsapp%20image%202020-04-08%20at%2012.06.00-306x307.jpeg","n/YOl3mQvOtngaMVIBnkdQ==":"whatsapp%20image%202020-04-08%20at%2012.11.50-306x308.jpeg","ZQOLzZk4/PkjwdOPP3cJ+g==":"whatsapp%20image%202020-04-08%20at%2012.17.39-306x309.jpeg","RUnIbE+VWZmxPHMFRHC9wQ==":"whatsapp%20image%202020-04-08%20at%2012.17.39-306x309.jpeg","24Kztvh6myUzdwCXmjBOyw==":"whatsapp%20image%202020-04-08%20at%2012.27.11-224x311.jpeg","zFivu58aRCPiN+n9kMZ3bg==":"whatsapp%20image%202020-04-08%20at%2012.46.26-224x226.jpg","SqXyp3nR07SAeQUaMre+jw==":"whatsapp%20image%202020-04-08%20at%2012.57.19-224x230.jpg","8YenI2fZaYpMJkoIafDEJg==":"whatsapp%20image%202020-04-08%20at%2013.25.23-224x223.jpg","rIR/ZHIoOz+Yt+XFeY+sEQ==":"whatsapp%20image%202020-04-08%20at%2013.32.50-224x234.jpg","Iu+ILrAExVeV8UzFCpE45A==":"whatsapp%20image%202020-04-08%20at%2013.32.50-224x234.jpeg","7J/L/51YaKsCA6HWtgVwcg==":"whatsapp%20image%202020-04-08%20at%2013.37.35-224x228.jpg","erCjMc4JVdeB8MRZL0URlA==":"whatsapp%20image%202020-04-08%20at%2013.51.44-224x224.jpg","LdyiK2y8ujnHDvL0A1jsTA==":"whatsapp%20image%202020-04-08%20at%2013.51.44-224x224.jpeg","R+ikP1sQvPUK2TN2HroSRw==":"whatsapp%20image%202020-04-08%20at%2013.25.23-224x223.jpeg","XTVdpP3u9SQQ15eZ6ZqOpA==":"marco_zero_-_recife_antigo_-_recife,_pernambuco,_brasil-800x600.jpg","o3LNQjC8zWFZnYlHGF+sOA==":"whatsapp%20image%202020-04-08%20at%2014.26.55-224x228.jpg","DyXG4XoKoH72n7baaLQVQw==":"marco_zero_-_recife_antigo_-_recife,_pernambuco,_brasil-1-800x600.jpg","3+1ikDsqlt8TMo2P5eeCPw==":"baha-2-612x876.png","PBbvPDYBUXIX9po3hlhtZg==":"antesqueomundoacabe-224x226.jpg","459Yo+ByDHM8Ez7p76l/Vg==":"imensobaha-224x233.jpg","my+N9f+2ge7S6L0Fm+EgnA==":"whatsapp%20image%202020-04-08%20at%2016.36.19-224x225.jpg","KVQ0p1dxFKJAf8SrgIhDHA==":"whatsapp%20image%202020-04-09%20at%2011.12.22-224x224.jpeg","3UKhJbq/mJxbJBEN8bEstA==":"whatsapp%20image%202020-04-09%20at%2015.43.49-224x223.jpg","5Y5wfyBZTeVl+P0hUgOOlA==":"whatsapp%20image%202020-04-09%20at%2015.47.30-224x225.jpg","OP6R5KK4Ut4Ur7zT5GQNOw==":"whatsapp%20image%202020-04-09%20at%2015.43.49-224x223.jpeg","LnP/RED3QkJkc0Q95ZFPNQ==":"sargaco1-224x227.jpg","lz2d0SUO9nUaTaMjvYkrVQ==":"sargaco2-224x222.jpg","jYXK+6+zUbBrC+/Fl29ooQ==":"sargaco2-224x222.jpeg","qEFLPl4LfcCf8ZqrsLgNxA==":"logobms-ok%20(1)-250x188.png","/KfIUep/hhXdfZUxx6rPzg==":"logobms-ok%20(1)-250x188.png","W9utbVf4a4qc5TvYSh+rvQ==":"logobms-ok-436x327.png","TY32KyfgL07qbYVIJIwLoQ==":"whatsapp%20image%202020-04-15%20at%2009.33.13-436x196.jpeg","ofKBfCJDU8s1i2fmRl+lLw==":"logobms-ok-800x600.png","Q4QlOyVhILix0v1aSL/jVw==":"whatsapp%20image%202020-04-14%20at%2015.12.54-744x1066.jpg","zTJdrcUNvDTzV92b6iP45Q==":"whatsapp%20image%202020-04-15%20at%2014.40.49-720x1280.jpg","EW/wu8eYXzKcSyjwAuko0Q==":"whatsapp%20image%202020-04-15%20at%2014.39.13-720x1280.jpg","8lNUmFmJ6ANFArRsGB1Pcw==":"whatsapp%20image%202020-04-15%20at%2014.56.36-1024x1280.jpg","f4BSJyyjUCwKoD2D6C244Q==":"whatsapp%20image%202020-04-15%20at%2014.39.13-720x1280.jpeg","sX/TIiUToN6qXJ0T5yQjXQ==":"whatsapp%20image%202020-04-15%20at%2016.36.24-1200x540.jpg","7sAcVL1KbcrK8wYocGMxYw==":"whatsapp%20image%202020-04-15%20at%2016.36.24-1200x540.jpeg","5okYBfvRYdVkvBXfb93apg==":"whatsapp%20image%202020-04-20%20at%2010.24.05-224x258.jpeg","vNeb05eIYNZopapTPIjZzQ==":"img-9207-750x462.jpeg","7P8sjWXPbeYQoFPl79H61g==":"dsc08331-750x563.jpeg","DgfS5sWk8hl4STfncS8pIQ==":"whatsapp%20image%202020-04-20%20at%2011.38.08-750x749.jpeg","XBvOJbdFCPYIHnyKlPbHtg==":"whatsapp%20image%202020-04-20%20at%2011.38.08-750x749.jpeg","rrGTGeZ15vDliVOj/tt/LQ==":"background3-1.jpg","uhGK7NjihQaolnnSEDxwKg==":"whatsapp%20image%202020-04-20%20at%2011.59.01-750x738.jpg","UsJN1aI1kjAw465hStJvYQ==":"whatsapp%20image%202020-04-20%20at%2012.01.37-750x744.jpg","gxuTQOpx+TPwgkTbBsvagA==":"whatsapp%20image%202020-04-20%20at%2012.01.37-750x744.jpeg","t/l/CHWk/c515r/q3KZg2Q==":"whatsapp%20image%202020-04-20%20at%2012.14.35-750x751.jpg","q1s6BiCvJrVHrT4E/hJ8lQ==":"whatsapp%20image%202020-04-20%20at%2012.14.35-750x751.jpeg","80G5xmBsQ+52E7SPxRl9NA==":"whatsapp%20image%202020-04-20%20at%2012.40.18-500x500.jpeg","dfoD0NGAyqUNC3GZTcePjA==":"whatsapp%20image%202020-04-20%20at%2013.23.59-1080x1080.jpg","kwCR3fiupeC4XAHyfMPW8A==":"whatsapp%20image%202020-04-20%20at%2015.46.05-224x213.jpg","hkJoAdvcX/c7feCf9Tt6sQ==":"whatsapp%20image%202020-04-22%20at%2010.11.11-224x126.jpeg","dtGVv5tTxSRDV6h/QbK0fg==":"sundiamond-224x224.jpg","AmAwm5nj5bU7QJSkr8ntQA==":"dsc01240-2000x1124.jpg","1Zau0aiaCTbx7QRcwg3W4A==":"dsc01240-2000x1124.jpeg","/jxKnCPm84zsawURmve1Kw==":"dsc01241-2000x1124.jpeg","87UsGTX3i0RZznX2hVn04Q==":"mbr-1920x1275.jpg","bjEwpaQeHrhLb0ijGM9G+w==":"estampa1-128x176.png","gPX+DQOMf3g45NRtaWuOrA==":"20200428_170234-2000x1125.png","WddRh0Sfzxn/LEFCWxw6cQ==":"whatsapp%20image%202020-05-08%20at%2013.51.10%20(1)-224x101.jpeg","fxq0dbVT/8EbKrued5EJlQ==":"whatsapp%20image%202020-05-08%20at%2013.51.10%20(1)-224x101.jpeg","dwlNqKy34169YmxrmLh9ug==":"whatsapp%20image%202020-05-08%20at%2014.25.56-224x224.jpg","IPfSWqs5F/Iw7EfQf9Apsg==":"whatsapp%20image%202020-05-08%20at%2014.31.21-224x227.jpg","HnbRpXJ+RQL0zJ96PqOzyQ==":"camisa1m-560x797.png","GeNd67P0Ow6crCVD3knURw==":"camisa1m-1-560x797.png","IiaWjKdoE10GXJgCsSUcgQ==":"estampa1invertida-01-01-4-936x1324.png","kx21MuqI06KfXk1fToSk6w==":"20200612_153402-900x900.png","WLbhkl94SkNycubBIocs4Q==":"20200611_171718-192x192.png","0PfwWadyXZMB8cKJanPmKg==":"20200612_154735-660x660.png","1jbQOyuZhn91f5HDDECXfg==":"whatsapp%20image%202020-06-12%20at%2015.51.49-660x660.jpg","uzrOqJg0Xlp9Z7T4H9QbRg==":"whatsapp%20image%202020-06-12%20at%2015.54.16-900x900.jpg","Ajpf1VIM1gHNaHfj+N4M4g==":"whatsapp%20image%202020-06-12%20at%2015.55.07-660x660.jpg","Bni1YWUog/Ho2OCZSlf69w==":"whatsapp%20image%202020-06-12%20at%2015.58.30-660x660.jpg","KQ++AR7yAd5I69y+zPQeVg==":"whatsapp%20image%202020-06-12%20at%2016.02.26-900x900.jpg","SwEyuhIId4f871h+JifPVg==":"whatsapp%20image%202020-06-12%20at%2016.01.20-660x660.jpg","tZalTXJVU1dCedZVmBeZrw==":"dsc01188-2000x1124.jpg","/EaGyVD7363GK4Lf/LGKGg==":"whatsapp%20image%202020-06-12%20at%2015.58.30-948x948.jpg","teynipw3dDmGVGmPAcYR4Q==":"whatsapp%20image%202020-06-12%20at%2016.02.26-948x948.jpg","EtlfRRiMuj5cPeb72PywYg==":"whatsapp%20image%202020-06-12%20at%2016.01.20-948x948.jpg","axvFFDz34jEFT8Ls89sF1g==":"whatsapp%20image%202020-06-12%20at%2015.58.30-510x510.jpg","YghuqRChMuGvLwMKCvYp4w==":"whatsapp-image-2020-06-12-at-15.58.30.jpeg","uBuXi0bTJieih+qNocJDcg==":"whatsapp-image-2020-06-12-at-16.02.26.jpeg","bqxU4BitchbfjTJ59AdpXA==":"whatsapp-image-2020-06-12-at-16.01.20.jpeg","IbYGDm47FOh6oubwkDhtcg==":"whatsapp-image-2020-06-11-at-16.49.22.jpeg","wUvh2qwWf1QY0Eo8IqBR0A==":"estampa1-2-122x168.png","Fuok12t+75DNLMH+Ag/waQ==":"whatsapp-image-2020-06-18-at-16.42.36.jpeg","8h6cdoMI31kGhuITjyN40w==":"whatsapp-image-2020-06-18-at-16.55.58.jpeg","oSkG9xMNZp0WUq6BQ1TL3Q==":"whatsapp-image-2020-07-22-at-10.28.04.jpeg","57x+lE6RyMeLNTwsAAmuKw==":"whatsapp-image-2020-08-07-at-07.25.46.jpeg","Bk/FXIaQZOCOgMmtSoH/8g==":"whatsapp-image-2020-08-07-at-07.25.46-1.jpeg","sa0rthBmOcSArnHL+9LkgQ==":"capa-ampulheta.png","CyzoqpjPMbiRJ5MCbb1lXA==":"whatsapp-image-2020-08-07-at-07.25.46-2.jpeg","1ROCV5AQjfLuY3fViqAgTw==":"whatsapp-image-2020-09-19-at-16.36.04.jpeg","sSTyB13HjEauTYxKnPmLsQ==":"whatsapp-image-2020-09-19-at-16.36.04-1.jpeg","OufTaMoJnOQNiQY21geglw==":"whatsapp-image-2020-10-01-at-11.29.54.jpeg","iyk1FgE5FrCuNKUsaumftA==":"whatsapp-image-2020-10-01-at-11.29.54-1.jpeg","xyD0G+03Tc3/Bb/7UCQSlA==":"whatsapp-image-2020-10-01-at-11.29.54-2.jpeg","OjzCMm1vfeXVZk84R63YgA==":"dsc01319.jpeg","vlqtqZoRYx6/GOG2wM5hOA==":"dsc01323.jpg","21KiKtf1EAZo0jhwpIoCMQ==":"dsc01323.jpeg","3br0CLrw7OQWoprajLxFFA==":"dsc01325.jpg","2s1aRiHeGF9XU3JYc4w8cA==":"arteampulhetaoficial.png"}